pylum/__init__.py
pylum/autoname.py
pylum/config.py
pylum/grating_coupler.py
pylum/loadmat.py
pylum/plot.py
pylum/run.py
pylum/sparameters.py
pylum/write_scripts.py
pylum-0.0.1.dist-info/LICENSE
pylum-0.0.1.dist-info/METADATA
pylum-0.0.1.dist-info/WHEEL
pylum-0.0.1.dist-info/top_level.txt
pylum-0.0.1.dist-info/RECORD
